lpc3d/LPC3D.py
lpc3d/__init__.py
lpc3d-0.1.3.dist-info/METADATA
lpc3d-0.1.3.dist-info/WHEEL
lpc3d-0.1.3.dist-info/entry_points.txt
lpc3d-0.1.3.dist-info/top_level.txt
lpc3d-0.1.3.dist-info/RECORD
