Metadata-Version: 2.1
Name: LPC3D
Version: 0.1.3
Summary: A package for LPC3D mesoscopic simulations
Author-email: El Hassane Lahrar <lahrar.el@gmail.com>, Céline Merlet <celine.merlet.fr@gmail.com>
License: AGPL-3.0-or-later
Keywords: LPC3D,simulation,OpenMP,GPU,computational science
Classifier: Programming Language :: Python :: 3
Classifier: License :: OSI Approved :: GNU Affero General Public License v3 or later (AGPLv3+)
Requires-Python: >=3.6
Requires-Dist: pystencils
Requires-Dist: numba
Requires-Dist: ipython
Requires-Dist: matplotlib
Requires-Dist: pyevtk
Provides-Extra: gpu
Requires-Dist: cupy-cuda; extra == "gpu"
